caseless_dictionary/__init__.py
caseless_dictionary/caseless_attribute_dict.py
caseless_dictionary/caseless_dict.py
caseless_dictionary/cases.py
caseless_dictionary/py.typed
caseless_dictionary-2.0.3.dist-info/licenses/LICENSE
caseless_dictionary-2.0.3.dist-info/METADATA
caseless_dictionary-2.0.3.dist-info/WHEEL
caseless_dictionary-2.0.3.dist-info/top_level.txt
caseless_dictionary-2.0.3.dist-info/RECORD
